CHANGELOG.rst
CONTRIBUTING.rst
MANIFEST.in
README.rst
TODO.rst
setup.py
bin/tvstats
tvstats/__init__.py
tvstats/graph.py
tvstats/info.py
tvstats/jsonhelper.py
tvstats/scraper.py
tvstats.egg-info/PKG-INFO
tvstats.egg-info/SOURCES.txt
tvstats.egg-info/dependency_links.txt
tvstats.egg-info/requires.txt
tvstats.egg-info/top_level.txt
tvstats/tests/__init__.py