Metadata-Version: 1.1
Name: tvstats
Version: 0.0.2
Summary: Scrape data of all the episodes of a Tv Series from IMDB
Home-page: http://github.com/leosartaj/tvstats
Author: Sartaj Singh
Author-email: singhsartaj94@gmail.com
License: MIT
Keywords: tv tvseries series IMBD scrape crawl
Platform: UNKNOWN
Classifier: Development Status :: 3 - Alpha
Classifier: License :: OSI Approved :: MIT License
Classifier: Environment :: Console
Classifier: Natural Language :: English
Classifier: Programming Language :: Python :: 2.7
